<?xml version="1.0" encoding="UTF-8"?>
<install type="module" version="1.5.1" method="upgrade">
	<name>Maian Menu</name>
	<author>Alao</author>
	<version>1.4.0</version>
	<description><![CDATA[  
	Menu Module
	</ol> ]]></description>
	<files>
		<filename module="mod_maianmenu">mod_maianmenu.php</filename>
		<filename>index.html</filename>
		<filename>tmpl/default.php</filename>
		<filename>tmpl/index.html</filename>
	</files>
	<params>
		<param name="f_display" type="radio" default="1"
			label="Show Free Downloads Menu"
			description="Display or Hide the menu. Show Navigation must be checked in settings">
			<option value="0">No</option>
			<option value="1">Yes</option>
		</param>
		<param name="p_display" type="radio" default="1"
			label="Show Most Popular Menu"
			description="Display or Hide the menu. Show Navigation must be checked in settings">
			<option value="0">No</option>
			<option value="1">Yes</option>
		</param>
		<param name="m_display" type="radio" default="1" label="Show Music Menu"
			description="Display or Hide the menu. Show Navigation must be checked in settings">
			<option value="0">No</option>
			<option value="1">Yes</option>
		</param>
		<param name="c_display" type="radio" default="1" label="Show Contact Menu"
			description="Display or Hide the menu. Show Navigation must be checked in settings">
			<option value="0">No</option>
			<option value="1">Yes</option>
		</param>
		<param name="l_display" type="radio" default="1" label="Show License Menu"
			description="Display or Hide the menu. Show Navigation must be checked in settings">
			<option value="0">No</option>
			<option value="1">Yes</option>
		</param>
	</params>
</install>